{
    "title": "東京大学史料編纂所報第19号（1984年）",
    "children": {
        "top": [],
        "口絵": [
            {
                "title": "胎蔵秘密略大軌（部分）",
                "page": "i-iii"
            },
            {
                "title": "＜口絵解説＞胎蔵秘密略大軌（部分）",
                "author": "石上、英一／厚谷、和雄",
                "page": "iv"
            },
            {
                "title": "識廬庵詩軸",
                "page": "v-vi"
            }
        ],
        "研究報告": [
            {
                "url": "http://www.hi.u-tokyo.ac.jp/publication/syoho/19/syoho0019-yoshida.pdf",
                "title": "『台記除目抜書』所収「雑事抄」について　：　『春除目抄』　・　『大間成文抄』関連史料として",
                "author": "吉田、早苗",
                "page": "1-22"
            },
            {
                "url": "http://www.hi.u-tokyo.ac.jp/publication/syoho/19/syoho0019-imaizumi.pdf",
                "title": "桃源瑞仙年譜稿",
                "author": "今泉、淑夫",
                "page": "23-50"
            }
        ],
        "本所出版物": [
            {
                "url": "http://www.hi.u-tokyo.ac.jp/publication/syoho/19/pub_shiryo-07-24.html",
                "title": "大日本史料第七編之二十四",
                "page": "51"
            },
            {
                "url": "http://www.hi.u-tokyo.ac.jp/publication/syoho/19/pub_shiryo-09-17.html",
                "title": "大日本史料第九編之十七",
                "page": "51*-52"
            },
            {
                "url": "http://www.hi.u-tokyo.ac.jp/publication/syoho/19/pub_kinsei-hosokawa-09.html",
                "title": "大日本近世史料「細川家史料」九",
                "page": "52*-53"
            },
            {
                "url": "http://www.hi.u-tokyo.ac.jp/publication/syoho/19/pub_kinsei-shichu-16.html",
                "title": "大日本近世史料「市中取締類集」十六",
                "page": "53*"
            },
            {
                "url": "http://www.hi.u-tokyo.ac.jp/publication/syoho/19/pub_kinsei-bakufu-16.html",
                "title": "大日本近世史料「幕府書物方日記」十六",
                "page": "53**-54"
            },
            {
                "url": "http://www.hi.u-tokyo.ac.jp/publication/syoho/19/pub_kinsei-kondou-01.html",
                "title": "大日本近世史料「近藤重蔵蝦夷地関係史料」一",
                "page": "54*-55"
            },
            {
                "url": "http://www.hi.u-tokyo.ac.jp/publication/syoho/19/pub_komonjo-iewake-21-02.html",
                "title": "大日本古文書　　家わけ第二十一「蜷川家文書之二」",
                "page": "55*"
            },
            {
                "url": "http://www.hi.u-tokyo.ac.jp/publication/syoho/19/pub_kokiroku-inokuma-06.html",
                "title": "大日本古記録「猪隈関白記」六",
                "page": "55**"
            },
            {
                "url": "http://www.hi.u-tokyo.ac.jp/publication/syoho/19/pub_kokiroku-gogumaiki-02.html",
                "title": "大日本古記録「後愚昧記」二",
                "page": "55***-57"
            },
            {
                "url": "http://www.hi.u-tokyo.ac.jp/publication/syoho/19/pub_kaigai-oranda-genbun-05.html",
                "title": "日本関係海外史料「オランダ商館長日記」原文編之五",
                "page": "57*-58"
            },
            {
                "url": "http://www.hi.u-tokyo.ac.jp/publication/syoho/19/pub_kaigai-oranda-yaku-04-ge.html",
                "title": "日本関係海外史料「オランダ商館長日記」訳文編之四（下）",
                "page": "58*-61"
            },
            {
                "url": "http://www.hi.u-tokyo.ac.jp/publication/syoho/19/pub_kaou-03-02.html",
                "title": "「花押かがみ」三　鎌倉時代二",
                "page": "61*"
            }
        ],
        "科学研究費による研究の報告": [
            {
                "title": "弘福寺及び東大寺を中心とした古代寺領荘園の歴史地理学的研究",
                "page": "62-70"
            },
            {
                "title": "幕藩制国家の解体と長州戦争",
                "page": "71-88"
            }
        ],
        "史料採訪": [
            {
                "url": "http://www.hi.u-tokyo.ac.jp/publication/syoho/19/saiho_KASUGA~1.HTM",
                "title": "春日大社及び東大寺図書館所蔵史料の調査・撮影"
            },
            {
                "url": "http://www.hi.u-tokyo.ac.jp/publication/syoho/19/saiho_KYOTOD~1.HTM",
                "title": "京都大学附属図書館所蔵古記録関連資料の調査"
            },
            {
                "url": "http://www.hi.u-tokyo.ac.jp/publication/syoho/19/saiho_MIEKEN~1.HTM",
                "title": "三重県伊勢市大湊支所史料調査"
            },
            {
                "url": "http://www.hi.u-tokyo.ac.jp/publication/syoho/19/saiho_NAGASA~1.HTM",
                "title": "長崎市立博物館所蔵史料の調査・撮影"
            },
            {
                "url": "http://www.hi.u-tokyo.ac.jp/publication/syoho/19/saiho_yakushiji.htm",
                "title": "奈良薬師寺所蔵史料の調査"
            },
            {
                "url": "http://www.hi.u-tokyo.ac.jp/publication/syoho/19/saiho_NISHIO~1.HTM",
                "title": "西尾市立図書館岩瀬文庫所蔵柳原家旧蔵史料の調査"
            },
            {
                "url": "http://www.hi.u-tokyo.ac.jp/publication/syoho/19/saiho_SHIBAT~1.HTM",
                "title": "新発田市立図書館所蔵の国絵図等の調査"
            },
            {
                "url": "http://www.hi.u-tokyo.ac.jp/publication/syoho/19/saiho_SUIFUM~1.HTM",
                "title": "水府明徳会彰考館所蔵史料の調査"
            },
            {
                "url": "http://www.hi.u-tokyo.ac.jp/publication/syoho/19/saiho_daigoji shiryou.html",
                "title": "醍醐寺史料調査"
            },
            {
                "url": "http://www.hi.u-tokyo.ac.jp/publication/syoho/19/saiho_hosokawake shiryou.html",
                "title": "細川家史料の調査・撮影"
            },
            {
                "url": "http://www.hi.u-tokyo.ac.jp/publication/syoho/19/saiho_myouhouin shozou shiryou.html",
                "title": "妙法院所蔵史料調査"
            },
            {
                "url": "http://www.hi.u-tokyo.ac.jp/publication/syoho/19/saiho_seikurain bunko.html",
                "title": "正倉院文書調査"
            }
        ]
    }
}